CHANGES.txt
CONTRIBUTORS.txt
MANIFEST.in
README.txt
setup.cfg
setup.py
collective/__init__.py
collective.ots.egg-info/PKG-INFO
collective.ots.egg-info/SOURCES.txt
collective.ots.egg-info/dependency_links.txt
collective.ots.egg-info/entry_points.txt
collective.ots.egg-info/namespace_packages.txt
collective.ots.egg-info/not-zip-safe
collective.ots.egg-info/paster_plugins.txt
collective.ots.egg-info/requires.txt
collective.ots.egg-info/top_level.txt
collective/ots/README.txt
collective/ots/__init__.py
collective/ots/config.py
collective/ots/configure.zcml
collective/ots/utils.py
collective/ots/browser/__init__.py
collective/ots/browser/configure.zcml
collective/ots/browser/summarizeview.pt
collective/ots/browser/summarizeview.py
collective/ots/profiles/default/actions.xml
collective/ots/tests/__init__.py
collective/ots/tests/base.py
collective/ots/tests/test_doctest.py
docs/HISTORY.txt
docs/INSTALL.txt
docs/LICENSE.GPL
docs/LICENSE.txt